{
  "@microsoft/generator-sharepoint": {
    "plusBeta": false,
    "isCreatingSolution": true,
    "nodeVersion": "16.19.0",
    "sdksVersions": {
      "@microsoft/microsoft-graph-client": "3.0.2",
      "@microsoft/teams-js": "2.4.1"
    },
    "version": "1.16.1",
    "environment": "spo",
    "libraryName": "react-personal-contacts",
    "libraryId": "05a9dee1-2de3-40f0-bee3-d511aca62e0a",
    "packageManager": "npm",
    "skipFeatureDeployment": true,
    "isDomainIsolated": false,
    "componentType": "webpart"
  }
}